polaris/__init__.py
polaris/admin.py
polaris/apps.py
polaris/collectstatic/__init__.py
polaris/cors.py
polaris/exceptions.py
polaris/integrations/__init__.py
polaris/integrations/custody.py
polaris/integrations/customers.py
polaris/integrations/fees.py
polaris/integrations/forms.py
polaris/integrations/info.py
polaris/integrations/quote.py
polaris/integrations/rails.py
polaris/integrations/sep31.py
polaris/integrations/toml.py
polaris/integrations/transactions.py
polaris/locale/__init__.py
polaris/locale/id/LC_MESSAGES/django.mo
polaris/locale/id/LC_MESSAGES/django.po
polaris/locale/pt/LC_MESSAGES/django.mo
polaris/locale/pt/LC_MESSAGES/django.po
polaris/locale/utils.py
polaris/management/__init__.py
polaris/management/commands/__init__.py
polaris/management/commands/execute_outgoing_transactions.py
polaris/management/commands/poll_outgoing_transactions.py
polaris/management/commands/process_pending_deposits.py
polaris/management/commands/testnet.py
polaris/management/commands/watch_transactions.py
polaris/middleware.py
polaris/migrations/0001_initial.py
polaris/migrations/0002_auto_20200921_2135.py
polaris/migrations/0003_auto_20201009_1300.py
polaris/migrations/0004_auto_20201120_1541.py
polaris/migrations/0005_auto_20210226_0053.py
polaris/migrations/0006_transaction_more_info_url.py
polaris/migrations/0007_transaction_on_change_callback.py
polaris/migrations/0008_transaction_pending_execution_attempt.py
polaris/migrations/0009_transaction_client_domain.py
polaris/migrations/0010_auto_20210809_1605.py
polaris/migrations/0011_transaction_amount_expected.py
polaris/migrations/0012_auto_20210918_2053.py
polaris/migrations/0013_auto_20211011_1956.py
polaris/migrations/0014_auto_20220211_0624.py
polaris/migrations/__init__.py
polaris/models.py
polaris/sep1/__init__.py
polaris/sep1/urls.py
polaris/sep1/views.py
polaris/sep10/__init__.py
polaris/sep10/token.py
polaris/sep10/urls.py
polaris/sep10/utils.py
polaris/sep10/views.py
polaris/sep12/__init__.py
django_polaris_bpv-2.7.0.dist-info/LICENSE
django_polaris_bpv-2.7.0.dist-info/METADATA
django_polaris_bpv-2.7.0.dist-info/WHEEL
django_polaris_bpv-2.7.0.dist-info/RECORD
