Metadata-Version: 2.3
Name: django-polaris-bpv
Version: 2.7.0
Summary: An extendable Django server for Stellar Ecosystem Proposals.
License: Apache-2.0
Keywords: stellar,anchor,polaris,sep,server
Author: Stellar Development Foundation
Author-email: jake@stellar.org
Requires-Python: >=3.10,<4.0
Classifier: Environment :: Web Environment
Classifier: Framework :: Django
Classifier: Framework :: Django :: 4.2
Classifier: Intended Audience :: Developers
Classifier: License :: OSI Approved :: Apache Software License
Classifier: Operating System :: OS Independent
Classifier: Programming Language :: Python
Classifier: Programming Language :: Python :: 3
Classifier: Programming Language :: Python :: 3.10
Classifier: Programming Language :: Python :: 3.11
Classifier: Programming Language :: Python :: 3.12
Classifier: Programming Language :: Python :: 3.13
Classifier: Programming Language :: Python :: 3 :: Only
Provides-Extra: dev-server
Provides-Extra: docs
Requires-Dist: aiohttp (>=3.7)
Requires-Dist: asgiref (>=3.2)
Requires-Dist: cryptography (>=41.0)
Requires-Dist: django (>=4.2)
Requires-Dist: django-cors-headers (>=3.7)
Requires-Dist: django-environ
Requires-Dist: django-model-utils (>=4.1)
Requires-Dist: djangorestframework (>=3.12)
Requires-Dist: gunicorn ; extra == "dev-server"
Requires-Dist: psycopg2-binary (>=2.9) ; extra == "dev-server"
Requires-Dist: pyjwt (>=2.1)
Requires-Dist: pytz
Requires-Dist: readthedocs-sphinx-ext (>=2.1,<3.0) ; extra == "docs"
Requires-Dist: sphinx (>=8.1,<9.0) ; extra == "docs"
Requires-Dist: sphinx-autodoc-typehints ; extra == "docs"
Requires-Dist: sphinx-rtd-theme (>=3.0,<4.0) ; extra == "docs"
Requires-Dist: sqlparse (>=0.4.2)
Requires-Dist: stellar-sdk[aiohttp] (>=10)
Requires-Dist: toml
Requires-Dist: watchdog ; extra == "dev-server"
Requires-Dist: whitenoise (>=5.3)
Project-URL: Bug Tracker, https://github.com/bp-ventures/django-polaris-bpv/issues
Project-URL: Documentation, https://django-polaris-bpv.readthedocs.io/en/latest/
Project-URL: Homepage, https://github.com/bp-ventures/django-polaris-bpv
Project-URL: Repository, https://github.com/bp-ventures/django-polaris-bpv
Project-URL: Release Notes, https://github.com/bp-ventures/django-polaris-bpv/releases
